pylinuxnetnamespace/README.MD
pylinuxnetnamespace/__init__.py
pylinuxnetnamespace/requirements.txt
pylinuxnetnamespace/thirdparty.json
pylinuxnetnamespace-0.10.dist-info/LICENSE.rst
pylinuxnetnamespace-0.10.dist-info/METADATA
pylinuxnetnamespace-0.10.dist-info/WHEEL
pylinuxnetnamespace-0.10.dist-info/top_level.txt
pylinuxnetnamespace-0.10.dist-info/RECORD
