Metadata-Version: 2.1
Name: pylinuxnetnamespace
Version: 0.10
Summary: Binds an IP-address to a subprocess through network namespaces - Linux only
Home-page: https://github.com/hansalemaos/pylinuxnetnamespace
Author: Johannes Fischer
Author-email: aulasparticularesdealemaosp@gmail.com
License: MIT
Keywords: subprocess,bind,ip,namespace,linux,network
Classifier: Development Status :: 4 - Beta
Classifier: Programming Language :: Python :: 3 :: Only
Classifier: Programming Language :: Python :: 3.10
Classifier: Topic :: Software Development :: Libraries :: Python Modules
Classifier: Topic :: Utilities
License-File: LICENSE.rst
